bigsort.py
bigsort-0.2.2.dist-info/METADATA
bigsort-0.2.2.dist-info/WHEEL
bigsort-0.2.2.dist-info/entry_points.txt
bigsort-0.2.2.dist-info/top_level.txt
bigsort-0.2.2.dist-info/RECORD
