Metadata-Version: 2.1
Name: bigsort
Version: 0.2.2
Summary: sort big file or streams
Home-page: https://github.com/laohur/bigsort
Author: laohur
Author-email: laohur@gmail.com
License: [Anti-996 License](https: // github.com/996icu/996.ICU/blob/master/LICENSE)
Keywords: bigsort,sort,external sort,big file sort
Requires-Python: >=3.0
Requires-Dist: psutil
Requires-Dist: logzero
